reverse_pred/__init__.py
reverse_pred/correlation_metrics.py
reverse_pred/decode_utils.py
reverse_pred/h5_utils.py
reverse_pred/model_to_model.py
reverse_pred/model_to_monkey.py
reverse_pred/monkey_to_model.py
reverse_pred/monkey_to_monkey.py
reverse_pred/prediction_utils.py
reverse_pred/regression_metrics.py
reverse_pred-0.1.3.dist-info/METADATA
reverse_pred-0.1.3.dist-info/WHEEL
reverse_pred-0.1.3.dist-info/licenses/LICENSE
reverse_pred-0.1.3.dist-info/RECORD
