Metadata-Version: 2.4
Name: reverse_pred
Version: 0.1.3
Summary: Library to run Reverse Predictivity
Project-URL: Homepage, https://github.com/vital-kolab/reverse_pred
Project-URL: Issues, https://github.com/vital-kolab/reverse_pred/issues
Author-email: Sabine Muzellec and Kohitij Kar <sabinem@yorku.ca>
License-Expression: MIT
License-File: LICENSE
Classifier: Operating System :: OS Independent
Classifier: Programming Language :: Python :: 3
Requires-Python: >=3.9
